divide/__init__.py
divide/divide_by_three.py
multiply/__init__.py
multiply/multiply_by_three.py
m5calc-0.0.1.dist-info/LICENSE.txt
m5calc-0.0.1.dist-info/METADATA
m5calc-0.0.1.dist-info/WHEEL
m5calc-0.0.1.dist-info/top_level.txt
m5calc-0.0.1.dist-info/RECORD
